jupyter_server_nbmodel/__init__.py
jupyter_server_nbmodel/_version.py
jupyter_server_nbmodel/event_logger.py
jupyter_server_nbmodel/extension.py
jupyter_server_nbmodel/handlers.py
jupyter_server_nbmodel/log.py
jupyter_server_nbmodel/event_schemas/cell_execution/v1.yaml
jupyter_server_nbmodel/tests/__init__.py
jupyter_server_nbmodel/tests/test_handlers.py
jupyter_server_nbmodel-0.1.1a2.data/data/etc/jupyter/jupyter_server_config.d/jupyter_server_nbmodel.json
jupyter_server_nbmodel-0.1.1a2.data/data/share/jupyter/labextensions/jupyter-server-nbmodel/package.json
jupyter_server_nbmodel-0.1.1a2.data/data/share/jupyter/labextensions/jupyter-server-nbmodel/static/728.f8d2e7dcd5b14868de42.js
jupyter_server_nbmodel-0.1.1a2.data/data/share/jupyter/labextensions/jupyter-server-nbmodel/static/73.8b9e263a3cc9fe0eb36c.js
jupyter_server_nbmodel-0.1.1a2.data/data/share/jupyter/labextensions/jupyter-server-nbmodel/static/remoteEntry.2db09543ece82f10f031.js
jupyter_server_nbmodel-0.1.1a2.data/data/share/jupyter/labextensions/jupyter-server-nbmodel/static/style.js
jupyter_server_nbmodel-0.1.1a2.data/data/share/jupyter/labextensions/jupyter-server-nbmodel/static/third-party-licenses.json
jupyter_server_nbmodel-0.1.1a2.data/data/share/jupyter/labextensions/jupyter-server-nbmodel/install.json
jupyter_server_nbmodel-0.1.1a2.dist-info/METADATA
jupyter_server_nbmodel-0.1.1a2.dist-info/WHEEL
jupyter_server_nbmodel-0.1.1a2.dist-info/licenses/LICENSE
jupyter_server_nbmodel-0.1.1a2.dist-info/RECORD
