Metadata-Version: 2.4
Name: jupyter_server_nbmodel
Version: 0.1.1a2
Dynamic: Keywords
Summary: A Jupyter Server extension to execute code cell from the server.
Project-URL: Homepage, https://github.com/datalayer/jupyter-server-nbmodel
Project-URL: Bug Tracker, https://github.com/datalayer/jupyter-server-nbmodel/issues
Project-URL: Repository, https://github.com/datalayer/jupyter-server-nbmodel.git
Author: Datalayer
License: BSD 3-Clause License
License-File: LICENSE
Classifier: Framework :: Jupyter
Classifier: Framework :: Jupyter :: JupyterLab
Classifier: Framework :: Jupyter :: JupyterLab :: 4
Classifier: Framework :: Jupyter :: JupyterLab :: Extensions
Classifier: Framework :: Jupyter :: JupyterLab :: Extensions :: Prebuilt
Classifier: License :: OSI Approved :: BSD License
Classifier: Programming Language :: Python
Classifier: Programming Language :: Python :: 3
Classifier: Programming Language :: Python :: 3.8
Classifier: Programming Language :: Python :: 3.9
Classifier: Programming Language :: Python :: 3.10
Classifier: Programming Language :: Python :: 3.11
Classifier: Programming Language :: Python :: 3.12
Requires-Python: >=3.8
Requires-Dist: jupyter-client>=8.6.2
Requires-Dist: jupyter-server<3,>=2.0.1
Provides-Extra: lab
Requires-Dist: jupyter-docprovider>=1.0.0b1; extra == 'lab'
Requires-Dist: jupyter-server-ydoc>=1.0.0b1; extra == 'lab'
Requires-Dist: jupyterlab>=4.2.0; extra == 'lab'
Provides-Extra: lint
Requires-Dist: mdformat-gfm>=0.3.5; extra == 'lint'
Requires-Dist: mdformat>0.7; extra == 'lint'
Requires-Dist: ruff>=0.4.0; extra == 'lint'
Provides-Extra: test
Requires-Dist: jupyter-server-fileid; extra == 'test'
Requires-Dist: jupyter-server-ydoc[test]>=1.0.0b1; extra == 'test'
Requires-Dist: pytest-cov; extra == 'test'
Requires-Dist: pytest-jupyter[server]>=0.6; extra == 'test'
Requires-Dist: pytest-timeout; extra == 'test'
Requires-Dist: pytest~=8.2; extra == 'test'
Provides-Extra: typing
Requires-Dist: mypy>=0.990; extra == 'typing'
